almanak/__init__.py
almanak/_base_client.py
almanak/_client.py
almanak/_compat.py
almanak/_constants.py
almanak/_exceptions.py
almanak/_files.py
almanak/_hasura.py
almanak/_legacy_response.py
almanak/_models.py
almanak/_qs.py
almanak/_resource.py
almanak/_response.py
almanak/_streaming.py
almanak/_types.py
almanak/_utils/__init__.py
almanak/_utils/_logs.py
almanak/_utils/_proxy.py
almanak/_utils/_streams.py
almanak/_utils/_sync.py
almanak/_utils/_transform.py
almanak/_utils/_typing.py
almanak/_utils/_utils.py
almanak/_utils/graphql.py
almanak/_utils/rest.py
almanak/_version.py
almanak/cli/__init__.py
almanak/cli/cli.py
almanak/mlops/__init__.py
almanak/mlops/cli.py
almanak/mlops/feature_store/__init__.py
almanak/mlops/feature_store/create_feature_view.py
almanak/mlops/feature_store/entity_records_to_rows.py
almanak/mlops/feature_store/feature_store.py
almanak/mlops/feature_store/launch_ui.py
almanak/mlops/feature_store/materialize_training_features.py
almanak/mlops/feature_store/utils/__init__.py
almanak/mlops/feature_store/utils/feast_object_serialisation.py
almanak/mlops/feature_store/utils/get_features_from_feature_view.py
almanak/mlops/train/__init__.py
almanak/mlops/train/_hasura.py
almanak/mlops/train/_upload_training_artifacts_to_gcs.py
almanak/pagination.py
almanak/resources/__init__.py
almanak/resources/agent/__init__.py
almanak/resources/agent/agent.py
almanak/resources/auth/__init__.py
almanak/resources/auth/api_keys.py
almanak/resources/auth/auth.py
almanak/resources/data.py
almanak/resources/deployment.py
almanak/resources/library/__init__.py
almanak/resources/library/artifacts/__init__.py
almanak/resources/library/artifacts/artifacts.py
almanak/resources/library/artifacts/versions.py
almanak/resources/library/library.py
almanak/resources/library/reference_queries.yaml
almanak/resources/library/strategies/__init__.py
almanak/resources/library/strategies/strategies.py
almanak/resources/library/strategies/versions.py
almanak/resources/optimization.py
almanak-1.0.9.dist-info/LICENSE
almanak-1.0.9.dist-info/METADATA
almanak-1.0.9.dist-info/NOTICE
almanak-1.0.9.dist-info/WHEEL
almanak-1.0.9.dist-info/entry_points.txt
almanak-1.0.9.dist-info/RECORD
