Metadata-Version: 2.3
Name: almanak
Version: 1.0.9
Summary: A powerful Python SDK for developing and deploying autonomous DeFi agents. Features agent-based modeling, state machine architecture, and non-custodial execution through Safe smart accounts
Author: engineering@almanak.co
Requires-Python: >=3.11,<3.12
Classifier: Programming Language :: Python :: 3
Classifier: Programming Language :: Python :: 3.10
Classifier: Programming Language :: Python :: 3.11
Classifier: Programming Language :: Python :: 3.12
Classifier: Programming Language :: Python :: 3.13
Provides-Extra: dev
Requires-Dist: aiofiles (>=24.1.0,<25.0.0)
Requires-Dist: aiohttp (>=3.11.11,<4.0.0)
Requires-Dist: almanak-src (>=0.0.11,<0.0.12)
Requires-Dist: anyio (>=4.8.0,<5.0.0)
Requires-Dist: click (>=8.1.8,<9.0.0)
Requires-Dist: google-cloud-bigquery (>=3.17.2)
Requires-Dist: google-cloud-logging (>=3.10.0)
Requires-Dist: google-cloud-secret-manager (>=2.20.0)
Requires-Dist: google-cloud-storage (>=2.14.0)
Requires-Dist: gql (>=3.5.0,<4.0.0)
Requires-Dist: httpx (>=0.28.1,<0.29.0)
Requires-Dist: kaleido (==0.2.1)
Requires-Dist: md-click-2 (>=0.0.1,<0.0.2) ; extra == "dev"
Requires-Dist: pandas (>=2.2.3,<3.0.0)
Requires-Dist: plotly (>=6.0.1,<7.0.0)
Requires-Dist: pwinput (>=1.0.3,<2.0.0)
Requires-Dist: pydantic (>=2.10.6,<3.0.0)
Requires-Dist: pydoc-markdown (>=4.8.2) ; extra == "dev"
Requires-Dist: pyjwt (>=2.10.1,<3.0.0)
Requires-Dist: python-dotenv (>=1.0.1,<2.0.0)
Requires-Dist: python-telegram-bot (>=22.0,<23.0)
Requires-Dist: requests (>=2.32.3,<3.0.0)
Requires-Dist: requests-toolbelt (>=1.0.0,<2.0.0)
Requires-Dist: retry (>=0.9.2,<0.10.0)
Requires-Dist: ruff (>=0.9.10,<0.10.0) ; extra == "dev"
Requires-Dist: selenium (>=4.31.0,<5.0.0)
Requires-Dist: setuptools (>=61) ; extra == "dev"
Requires-Dist: sqlalchemy (>=2.0.39,<3.0.0)
Requires-Dist: sqlmodel (>=0.0.24,<0.0.25)
Requires-Dist: streamlit (>=1.44.1,<2.0.0)
Requires-Dist: twine (>=6.1.0,<7.0.0) ; extra == "dev"
Requires-Dist: web3 (>=6.8.0,<7.0.0)
Requires-Dist: wheel (==0.34.1) ; extra == "dev"
